nptime.py
nptime-1.1.dist-info/DESCRIPTION.rst
nptime-1.1.dist-info/METADATA
nptime-1.1.dist-info/RECORD
nptime-1.1.dist-info/WHEEL
nptime-1.1.dist-info/metadata.json
nptime-1.1.dist-info/top_level.txt
