Metadata-Version: 2.0
Name: nptime
Version: 1.1
Summary: Extends datetime.time, allowing time arithmetic
Home-page: https://github.com/tgs/nptime
Author: Thomas Grenfell Smith
Author-email: thomathom@gmail.com
License: 3-clause BSD
Keywords: time datetime timedelta
Platform: UNKNOWN
Classifier: Development Status :: 4 - Beta
Classifier: Programming Language :: Python
Classifier: Intended Audience :: Developers
Classifier: License :: OSI Approved :: BSD License
Classifier: Operating System :: OS Independent
